README.txt
setup.py
docs/HISTORY.txt
docs/INSTALL.txt
docs/LICENSE.GPL
docs/LICENSE.txt
plonetheme/__init__.py
plonetheme.jsjamba.egg-info/PKG-INFO
plonetheme.jsjamba.egg-info/SOURCES.txt
plonetheme.jsjamba.egg-info/dependency_links.txt
plonetheme.jsjamba.egg-info/entry_points.txt
plonetheme.jsjamba.egg-info/namespace_packages.txt
plonetheme.jsjamba.egg-info/not-zip-safe
plonetheme.jsjamba.egg-info/requires.txt
plonetheme.jsjamba.egg-info/top_level.txt
plonetheme/jsjamba/__init__.py
plonetheme/jsjamba/configure.zcml
plonetheme/jsjamba/tests.py
plonetheme/jsjamba/Extensions/Install.py
plonetheme/jsjamba/browser/__init__.py
plonetheme/jsjamba/browser/configure.zcml
plonetheme/jsjamba/browser/interfaces.py
plonetheme/jsjamba/browser/viewlets/__init__.py
plonetheme/jsjamba/profiles/default/cssregistry.xml
plonetheme/jsjamba/profiles/default/jsregistry.xml
plonetheme/jsjamba/profiles/default/metadata.xml
plonetheme/jsjamba/profiles/default/plonetheme.jsjamba_default.txt
plonetheme/jsjamba/profiles/default/propertiestool.xml
plonetheme/jsjamba/profiles/default/skins.xml
plonetheme/jsjamba/profiles/default/viewlets.xml
plonetheme/jsjamba/profiles/uninstall/cssregistry.xml
plonetheme/jsjamba/profiles/uninstall/propertiestool.xml
plonetheme/jsjamba/profiles/uninstall/skins.xml
plonetheme/jsjamba/profiles/uninstall/viewlets.xml
plonetheme/jsjamba/skins/jsjamba_images/CONTENT.txt
plonetheme/jsjamba/skins/jsjamba_images/body_bg.png
plonetheme/jsjamba/skins/jsjamba_images/logo.png
plonetheme/jsjamba/skins/jsjamba_styles/CONTENT.txt
plonetheme/jsjamba/skins/jsjamba_styles/authoring.css.dtml
plonetheme/jsjamba/skins/jsjamba_styles/base_properties.props
plonetheme/jsjamba/skins/jsjamba_styles/jamba.css.dtml
plonetheme/jsjamba/skins/jsjamba_styles/jamba.js
plonetheme/jsjamba/skins/jsjamba_styles/portlets.css.dtml
plonetheme/jsjamba/skins/jsjamba_styles/print.css.dtml
plonetheme/jsjamba/skins/jsjamba_styles/public.css.dtml
plonetheme/jsjamba/skins/jsjamba_templates/CONTENT.txt
plonetheme/jsjamba/skins/jsjamba_templates/main_template.pt